[{"id":"general","name":"partner-general","category":"Partner Chat","messageCount":59582},{"id":"how-to-partner","name":"how-to-partner","category":"Partner Chat","messageCount":7},{"id":"collabs","name":"collabs","category":"All Roles","messageCount":426},{"id":"announcements","name":"announcements","category":"Rare Official","messageCount":678},{"id":"ask-rare","name":"ask-rare-2-electric-boogaloo","category":"Rare Official","messageCount":6948},{"id":"rare-answers","name":"rare-answers","category":"Rare Official","messageCount":58},{"id":"roadmap","name":"roadmap","category":"Rare Official","messageCount":21},{"id":"tavern","name":"tavern","category":"Tavern","messageCount":13784},{"id":"drops-feedback","name":"drops-feedback","category":"Tavern","messageCount":1885}]